wenet_stt.libs/libfst-8c44c13e.so.8.0.0
wenet_stt.libs/libtensorpipe-7d524e69.so
wenet_stt.libs/libtorch-d95ee835.so
wenet_stt.libs/libtorch_cpu-91c035fe.so
wenet_stt.libs/libgomp-7c85b1e2-8ff38fd8.so.1
wenet_stt.libs/libc10-241f0ee2.so
wenet_stt-0.2.0.dist-info/WHEEL
wenet_stt-0.2.0.dist-info/top_level.txt
wenet_stt-0.2.0.dist-info/METADATA
wenet_stt-0.2.0.dist-info/LICENSE
wenet_stt-0.2.0.dist-info/RECORD
wenet_stt/libwenet_stt_lib.so
wenet_stt/wrapper.py
wenet_stt/__init__.py
wenet_stt/__main__.py
