Metadata-Version: 2.1
Name: wenet-stt
Version: 0.2.0
Summary: Simple Python library, distributed via binary wheels with few direct dependencies, for easily using wav2vec 2.0 models for speech recognition.
Home-page: https://github.com/daanzu/wenet_stt_python
Author: David Zurow
Author-email: daanzu@gmail.com
License: AGPL-3.0
Project-URL: Bug Reports, https://github.com/daanzu/wenet_stt/issues
Project-URL: Funding, https://github.com/sponsors/daanzu
Project-URL: Source, https://github.com/daanzu/wenet_stt/
Platform: UNKNOWN
Classifier: Development Status :: 4 - Beta
Classifier: Intended Audience :: Developers
Classifier: License :: OSI Approved :: GNU Affero General Public License v3
Classifier: Programming Language :: Python :: 3
Classifier: Programming Language :: Python :: 3.6
Classifier: Programming Language :: Python :: 3.7
Classifier: Programming Language :: Python :: 3.8
Classifier: Programming Language :: Python :: 3.9
Requires-Python: >=3.6, <4
License-File: LICENSE
Requires-Dist: cffi (~=1.12)
Requires-Dist: numpy (!=1.19.4,~=1.16)
Provides-Extra: test
Requires-Dist: pytest ; extra == 'test'
